<?xml version="1.0" encoding="UTF-8"?>
<QCARConfig xmlns:xsi="http://www.w3.org/2001/XMLSchema-instance" xsi:noNamespaceSchemaLocation="qcar_config.xsd">
  <Tracking>
    <ImageTarget name="INDUKTOR" size="100.000000 119.920319" />
    <ImageTarget name="POTENSIOMETER" size="100.000000 119.721115" />
    <ImageTarget name="MULTIMETER" size="100.000000 119.721115" />
    <ImageTarget name="IC" size="100.000000 119.721115" />
    <ImageTarget name="ZENERDIODE" size="100.000000 119.920319" />
    <ImageTarget name="TRANSISTOR" size="100.000000 119.920319" />
    <ImageTarget name="RESISTOR" size="100.000000 120.717133" />
    <ImageTarget name="PHOTODIODE" size="100.000000 119.920319" />
    <ImageTarget name="LED" size="100.000000 120.916336" />
    <ImageTarget name="DIODE" size="100.000000 120.916336" />
    <ImageTarget name="CAPASITOR" size="100.000000 121.314743" />
    <ImageTarget name="DIOD1" size="400.000000 372.972961" />
    <ImageTarget name="TR1" size="400.000000 400.000000" />
    <ImageTarget name="RES1" size="400.000000 400.000000" />
    <ImageTarget name="PD1" size="400.000000 240.104172" />
    <ImageTarget name="ZEN1" size="400.000000 200.000000" />
    <ImageTarget name="LED1" size="400.000000 400.000000" />
    <ImageTarget name="CAP1" size="400.000000 284.158417" />
  </Tracking>
</QCARConfig>
